copasi_petab_importer/PEtab.py
copasi_petab_importer/__init__.py
copasi_petab_importer/_version.py
copasi_petab_importer/convert_all_petab.py
copasi_petab_importer/convert_benchmark.py
copasi_petab_importer/convert_petab.py
copasi_petab_importer/petab.ui
copasi_petab_importer-1.0.9.dist-info/METADATA
copasi_petab_importer-1.0.9.dist-info/WHEEL
copasi_petab_importer-1.0.9.dist-info/entry_points.txt
copasi_petab_importer-1.0.9.dist-info/top_level.txt
copasi_petab_importer-1.0.9.dist-info/RECORD
