Metadata-Version: 2.4
Name: copasi-petab-importer
Version: 1.0.9
Summary: COPASI PEtab Importer
Home-page: https://github.com/copasi/python-petab-importer
Author: Frank T. Bergmann
Author-email: frank.bergmann@bioquant.uni-heidelberg.de
License: Artistic-2.0
Requires-Dist: numpy
Requires-Dist: pandas
Requires-Dist: python-copasi
Requires-Dist: python-libsbml
Requires-Dist: pyyaml
Provides-Extra: gui
Requires-Dist: PyQt5; extra == "gui"
Dynamic: author
Dynamic: author-email
Dynamic: description
Dynamic: description-content-type
Dynamic: home-page
Dynamic: license
Dynamic: provides-extra
Dynamic: requires-dist
Dynamic: summary
